sqint/__init__.py
sqint/sqint copy.py
sqint/sqint.css
sqint/sqint.py
sqint-0.1a1.dist-info/LICENSE
sqint-0.1a1.dist-info/METADATA
sqint-0.1a1.dist-info/WHEEL
sqint-0.1a1.dist-info/entry_points.txt
sqint-0.1a1.dist-info/top_level.txt
sqint-0.1a1.dist-info/zip-safe
sqint-0.1a1.dist-info/RECORD
