Metadata-Version: 2.1
Name: sqint
Version: 0.1a1
Summary: Example package description
Home-page: https://github.com/cdelker/sqint
Author: Collin J. Delker
Author-email: code@collindelker.com
License: License :: OSI Approved :: MIT License
Keywords: sqlite,database,tui
Classifier: Development Status :: 3 - Alpha
Classifier: Programming Language :: Python
Classifier: Topic :: Database
Classifier: Topic :: Database :: Front-Ends
Classifier: License :: OSI Approved :: MIT License
License-File: LICENSE
Requires-Dist: textual (>=0.18)
